main.py
dungngo_crypto_sentiment_mcp-0.1.2.dist-info/licenses/LICENSE
dungngo_crypto_sentiment_mcp-0.1.2.dist-info/METADATA
dungngo_crypto_sentiment_mcp-0.1.2.dist-info/WHEEL
dungngo_crypto_sentiment_mcp-0.1.2.dist-info/entry_points.txt
dungngo_crypto_sentiment_mcp-0.1.2.dist-info/top_level.txt
dungngo_crypto_sentiment_mcp-0.1.2.dist-info/RECORD
