Metadata-Version: 2.4
Name: dungngo-crypto-sentiment-mcp
Version: 0.1.2
Summary: An MCP server that delivers cryptocurrency sentiment analysis to AI agents. (republished for testing)
Author-email: dungngo <test@dungngo.dev>
Requires-Python: >=3.13
License-File: LICENSE
Requires-Dist: mcp[cli]>=1.4.1
Requires-Dist: sanpy>=0.12.0
Dynamic: license-file
